nonebot_plugin_mcqq_mcrcon/__init__.py
nonebot_plugin_mcqq_mcrcon/data_source.py
nonebot_plugin_mcqq_mcrcon/utils.py
nonebot_plugin_mcqq_mcrcon-1.1.5.post2.dist-info/LICENSE
nonebot_plugin_mcqq_mcrcon-1.1.5.post2.dist-info/METADATA
nonebot_plugin_mcqq_mcrcon-1.1.5.post2.dist-info/WHEEL
nonebot_plugin_mcqq_mcrcon-1.1.5.post2.dist-info/top_level.txt
nonebot_plugin_mcqq_mcrcon-1.1.5.post2.dist-info/RECORD
