Metadata-Version: 2.1
Name: nonebot-plugin-mcqq-mcrcon
Version: 1.1.5.post2
Summary: 基于NoneBot的QQ群聊与Minecraft Server消息互通插件
Home-page: https://github.com/17TheWord/nonebot-plugin-mcqq
Author: 17TheWord
Author-email: 17theword@gmail.com
Classifier: Programming Language :: Python :: 3.9
Classifier: License :: OSI Approved :: GNU Affero General Public License v3
Classifier: Operating System :: OS Independent
License-File: LICENSE
Requires-Dist: mcqq-tool (>=0.0.1)
Requires-Dist: nonebot2 (>=2.0.0rc3)
Requires-Dist: nonebot-adapter-onebot (>=2.1.1)
Requires-Dist: nonebot-plugin-guild-patch (>=0.2.0)
Requires-Dist: websockets (>=10.3)
Requires-Dist: mcrcon (>=0.7.0)
